Metadata-Version: 2.1
Name: odoo14-addon-stock_location_last_inventory_date
Version: 14.0.2.0.1.dev4
Summary: Show the last inventory date for a leaf location
Home-page: https://github.com/OCA/stock-logistics-warehouse
Author: Camptocamp, Odoo Community Association (OCA)
Author-email: support@odoo-community.org
License: AGPL-3
Classifier: Programming Language :: Python
Classifier: Framework :: Odoo
Classifier: Framework :: Odoo :: 14.0
Classifier: License :: OSI Approved :: GNU Affero General Public License v3
Classifier: Development Status :: 3 - Alpha
Requires-Python: >=3.6
Requires-Dist: odoo<14.1dev,>=14.0a
